qollage-0.9.0.dist-info/METADATA
qollage-0.9.0.dist-info/WHEEL
qollage-0.9.0.dist-info/licenses/LICENSE
qollage/DEPENDENCIES
qollage/__init__.py
qollage/qollage.cpython-312-x86_64-linux-gnu.so
qollage/qollage.pyi
qollage-0.9.0.dist-info/RECORD
