Metadata-Version: 2.4
Name: qollage
Version: 0.9.0
Requires-Dist: qoqo>=1.19,<2.0
Requires-Dist: qoqo-calculator-pyo3>=1.5,<1.6
Requires-Dist: pillow>=10.3.0
Requires-Dist: ipython>=8.12
Requires-Dist: tomli ; extra == 'docs'
Requires-Dist: numpy ; extra == 'docs'
Requires-Dist: sphinx>=2.1 ; extra == 'docs'
Requires-Dist: nbsphinx ; extra == 'docs'
Requires-Dist: pygments ; extra == 'docs'
Requires-Dist: recommonmark ; extra == 'docs'
Requires-Dist: myst-parser ; extra == 'docs'
Requires-Dist: sphinx-rtd-theme ; extra == 'docs'
Provides-Extra: docs
License-File: LICENSE
Maintainer-email: HQS Quantum Simulations GmbH <info@quantumsimulations.de>
License: Apache-2.0 AND Apache-2.0 with LLVM-exception AND MIT AND Unicode-DFS-2016 AND
Requires-Python: >=3.10
